stellaris/__init__.py
stellaris/constants.py
stellaris/database.py
stellaris/manager.py
stellaris/node/__init__.py
stellaris/node/main.py
stellaris/node/nodes.json
stellaris/node/nodes_manager.py
stellaris/node/utils.py
stellaris/scripts/setup.sh
stellaris/scripts/setup_db.sh
stellaris/transactions/__init__.py
stellaris/transactions/coinbase_transaction.py
stellaris/transactions/transaction.py
stellaris/transactions/transaction_input.py
stellaris/transactions/transaction_output.py
stellaris/utils/block_utils.py
stellaris/utils/general.py
stellaris_chain-0.1.0.dist-info/licenses/LICENSE
stellaris_chain-0.1.0.dist-info/METADATA
stellaris_chain-0.1.0.dist-info/WHEEL
stellaris_chain-0.1.0.dist-info/entry_points.txt
stellaris_chain-0.1.0.dist-info/top_level.txt
stellaris_chain-0.1.0.dist-info/RECORD
