Metadata-Version: 2.4
Name: stellaris-chain
Version: 0.1.0
Summary: A blockchain implementation in Python
Author: Stellaris Chain Team
License: Attribution-NonCommercial-ShareAlike 4.0 International
Project-URL: Homepage, https://github.com/StellarisChain/stellaris
Project-URL: Repository, https://github.com/StellarisChain/stellaris
Project-URL: Issues, https://github.com/StellarisChain/stellaris/issues
Classifier: Development Status :: 3 - Alpha
Classifier: Intended Audience :: Developers
Classifier: License :: OSI Approved :: MIT License
Classifier: Programming Language :: Python :: 3
Classifier: Programming Language :: Python :: 3.10
Classifier: Programming Language :: Python :: 3.11
Classifier: Programming Language :: Python :: 3.12
Classifier: Topic :: Software Development :: Libraries :: Python Modules
Classifier: Topic :: Security :: Cryptography
Requires-Python: >=3.10
License-File: LICENSE
Requires-Dist: pydantic>=2.11.5
Requires-Dist: fastapi>=0.115.12
Requires-Dist: httpx==0.28.1
Requires-Dist: aiohttp>=3.8.0
Requires-Dist: requests>=2.28.0
Requires-Dist: uvicorn>=0.34.2
Requires-Dist: cryptography>=45.0.3
Requires-Dist: colorama==0.4.6
Requires-Dist: python-dotenv>=0.9.9
Requires-Dist: rsa>=4.9.1
Requires-Dist: psutil>=7.0.0
Requires-Dist: kytan-py>=0.1.0
Requires-Dist: modern-benchmark>=0.1.0
Requires-Dist: libp2p>=0.2.8
Requires-Dist: miniupnpc>=2.3.3
Requires-Dist: pystun3>=2.0.0
Requires-Dist: docker>=7.0.0
Requires-Dist: fastecdsa>=2.3.2
Requires-Dist: asyncpg~=0.29.0
Requires-Dist: pickleDB~=0.9.2
Requires-Dist: base58>=1.0.3
Requires-Dist: slowapi
Requires-Dist: starlette
Requires-Dist: kvprocessor>=0.2.14
Requires-Dist: p2pd
Provides-Extra: dev
Requires-Dist: mypy==1.16.0; extra == "dev"
Requires-Dist: pytest==8.3.5; extra == "dev"
Requires-Dist: maturin; extra == "dev"
Requires-Dist: pip-tools; extra == "dev"
Dynamic: license-file
